setup.py
yandex_kassa/__init__.py
yandex_kassa/version.py
yandex_kassa.egg-info/PKG-INFO
yandex_kassa.egg-info/SOURCES.txt
yandex_kassa.egg-info/dependency_links.txt
yandex_kassa.egg-info/top_level.txt