Metadata-Version: 1.1
Name: yandex-kassa
Version: 0.0.5
Summary: empty
Home-page: https://github.com/k0st1an/yandex-kassa
Author: Konstantin Kruglov
Author-email: kruglovk@gmail.com
License: Apache License Version 2.0
Platform: UNKNOWN
Classifier: Development Status :: 3 - Alpha
Classifier: License :: OSI Approved :: Apache Software License
Classifier: Programming Language :: Python :: 3 :: Only
Classifier: Operating System :: POSIX :: Linux
